{"SURVIVAL":{"offHandItem":{"==":"org.bukkit.inventory.ItemStack","v":2730,"type":"AIR","amount":0},"armorContents":{"0":{"==":"org.bukkit.inventory.ItemStack","v":2730,"type":"IRON_BOOTS","meta":{"==":"ItemMeta","meta-type":"UNSPECIFIC","enchants":{"DEPTH_STRIDER":3,"PROTECTION_FIRE":4},"repair-cost":1,"Damage":47}},"1":{"==":"org.bukkit.inventory.ItemStack","v":2730,"type":"IRON_LEGGINGS","meta":{"==":"ItemMeta","meta-type":"UNSPECIFIC","enchants":{"PROTECTION_FIRE":4,"DURABILITY":3},"repair-cost":1,"Damage":35}},"2":{"==":"org.bukkit.inventory.ItemStack","v":2730,"type":"IRON_CHESTPLATE","meta":{"==":"ItemMeta","meta-type":"UNSPECIFIC","enchants":{"PROTECTION_ENVIRONMENTAL":4,"THORNS":2,"DURABILITY":3},"repair-cost":1,"Damage":35}},"3":{"==":"org.bukkit.inventory.ItemStack","v":2730,"type":"IRON_HELMET","meta":{"==":"ItemMeta","meta-type":"UNSPECIFIC","enchants":{"PROTECTION_FIRE":3},"repair-cost":1,"Damage":47}}},"bedSpawnLocation":{"==":"org.bukkit.Location","world":"Killer_Island","x":-1410.5,"y":108.0625,"z":369.5,"pitch":0.0,"yaw":0.0},"inventoryContents":{"10":{"==":"org.bukkit.inventory.ItemStack","v":2730,"type":"LAVA_BUCKET"},"11":{"==":"org.bukkit.inventory.ItemStack","v":2730,"type":"LAVA_BUCKET"},"12":{"==":"org.bukkit.inventory.ItemStack","v":2730,"type":"LAVA_BUCKET"},"34":{"==":"org.bukkit.inventory.ItemStack","v":2730,"type":"WHITE_SHULKER_BOX","meta":{"==":"ItemMeta","meta-type":"TILE_ENTITY","internal":"H4sIAAAAAAAA\/7XQT0+DMBgG8AcYhNVozKJRv4on45+DNxO9Nx2UrgFaQt8d9u1t6IBFErPLemnT\/N6nb18GMNy8NraoPwxpOvwItUb6SbJ1DMBVhNV3Ywk5Yl1i02oji15U9DycRE8R0je7N34\/0ijQh5m6rhFuxztL2prJMyQkVI7sa7jH40kB9dYovpOi0UZhTI4vlpxcLHm1GJzrDspnu8Xg0kDvZqp9JPdpdpryy4izM\/D1iPOAb0+a8H327s+\/EmTvohVKYljH4vWieLsvajm9Eo+QBXg\/w8LaWpZ8K2W16GkT9NOsKz844sKU3JGUzf\/NAb9cQxd4uwIAAA==","blockMaterial":"WHITE_SHULKER_BOX"}},"35":{"==":"org.bukkit.inventory.ItemStack","v":2730,"type":"ARROW"},"36":{"==":"org.bukkit.inventory.ItemStack","v":2730,"type":"IRON_BOOTS","meta":{"==":"ItemMeta","meta-type":"UNSPECIFIC","enchants":{"DEPTH_STRIDER":3,"PROTECTION_FIRE":4},"repair-cost":1,"Damage":47}},"37":{"==":"org.bukkit.inventory.ItemStack","v":2730,"type":"IRON_LEGGINGS","meta":{"==":"ItemMeta","meta-type":"UNSPECIFIC","enchants":{"PROTECTION_FIRE":4,"DURABILITY":3},"repair-cost":1,"Damage":35}},"38":{"==":"org.bukkit.inventory.ItemStack","v":2730,"type":"IRON_CHESTPLATE","meta":{"==":"ItemMeta","meta-type":"UNSPECIFIC","enchants":{"PROTECTION_ENVIRONMENTAL":4,"THORNS":2,"DURABILITY":3},"repair-cost":1,"Damage":35}},"39":{"==":"org.bukkit.inventory.ItemStack","v":2730,"type":"IRON_HELMET","meta":{"==":"ItemMeta","meta-type":"UNSPECIFIC","enchants":{"PROTECTION_FIRE":3},"repair-cost":1,"Damage":47}},"0":{"==":"org.bukkit.inventory.ItemStack","v":2730,"type":"DIAMOND_PICKAXE","meta":{"==":"ItemMeta","meta-type":"UNSPECIFIC","enchants":{"DIG_SPEED":4,"LOOT_BONUS_BLOCKS":2},"repair-cost":15,"Damage":766}},"1":{"==":"org.bukkit.inventory.ItemStack","v":2730,"type":"DIAMOND_SWORD","meta":{"==":"ItemMeta","meta-type":"UNSPECIFIC","enchants":{"KNOCKBACK":2,"LOOT_BONUS_MOBS":3,"DAMAGE_ALL":4},"repair-cost":1,"Damage":44}},"2":{"==":"org.bukkit.inventory.ItemStack","v":2730,"type":"DIAMOND_AXE","meta":{"==":"ItemMeta","meta-type":"UNSPECIFIC","enchants":{"DIG_SPEED":4,"DURABILITY":3},"Damage":2}},"3":{"==":"org.bukkit.inventory.ItemStack","v":2730,"type":"DIAMOND_SHOVEL","meta":{"==":"ItemMeta","meta-type":"UNSPECIFIC","enchants":{"DIG_SPEED":4},"Damage":131}},"4":{"==":"org.bukkit.inventory.ItemStack","v":2730,"type":"BOW","meta":{"==":"ItemMeta","meta-type":"UNSPECIFIC","display-name":"{\"text\":\"Oathbow\"}","enchants":{"ARROW_INFINITE":1,"ARROW_DAMAGE":4,"DURABILITY":3},"repair-cost":7,"Damage":127}},"5":{"==":"org.bukkit.inventory.ItemStack","v":2730,"type":"IRON_INGOT","amount":36},"6":{"==":"org.bukkit.inventory.ItemStack","v":2730,"type":"LAVA_BUCKET"},"7":{"==":"org.bukkit.inventory.ItemStack","v":2730,"type":"COOKED_BEEF","amount":57},"8":{"==":"org.bukkit.inventory.ItemStack","v":2730,"type":"TORCH","amount":22},"9":{"==":"org.bukkit.inventory.ItemStack","v":2730,"type":"LAVA_BUCKET"}},"enderChestContents":{"0":{"==":"org.bukkit.inventory.ItemStack","v":2730,"type":"OBSIDIAN","amount":10}},"potions":[],"stats":{"ex":"0.5242644","ma":"300","fl":"19","el":"39","xp":"0.55548877","hp":"20.0","txp":"19548","sa":"0.0","ft":"-20","fd":"0.0","ra":"300"}}}