{"SURVIVAL":{"enderChestContents":{"11":{"==":"org.bukkit.inventory.ItemStack","v":2730,"type":"ENDER_PEARL","amount":16},"12":{"==":"org.bukkit.inventory.ItemStack","v":2730,"type":"LAPIS_LAZULI","amount":64},"13":{"==":"org.bukkit.inventory.ItemStack","v":2730,"type":"LAPIS_LAZULI","amount":27},"14":{"==":"org.bukkit.inventory.ItemStack","v":2730,"type":"ENDER_PEARL","amount":16},"15":{"==":"org.bukkit.inventory.ItemStack","v":2730,"type":"GOLDEN_SHOVEL"},"17":{"==":"org.bukkit.inventory.ItemStack","v":2730,"type":"RAW_IRON","amount":30},"18":{"==":"org.bukkit.inventory.ItemStack","v":2730,"type":"PLAYER_HEAD","meta":{"==":"ItemMeta","meta-type":"SKULL","display-name":"{\"translate\":\"%s %s\",\"with\":[{\"translate\":\"entity.minecraft.enderman\"},{\"translate\":\"Head\"}],\"italic\":false}","lore":["{\"extra\":[{\"bold\":false,\"italic\":false,\"underlined\":false,\"strikethrough\":false,\"obfuscated\":false,\"color\":\"dark_gray\",\"text\":\"mob:enderman\"}],\"text\":\"\"}"],"internal":"H4sIAAAAAAAA\/03PTU6DQBwF8H9NTRBdeQ8TagumJi6I1HZIZ5B2iszsaJkKdKZt+FDhLu51rfcwnsA7uHAt7ly+vF9e8nQAHU7mm0rK23y3TqXQoEsiJeA0znf7RERxcTkizmiGbaKD3qK9yMtUFEegleKprHJR6ADQ0eAwiGQl4F3UrsHDxIhDV65qZLWZzg3poWx\/gbZBvbxGFlJtP7GtaT38Z80yujMl67sJ3\/rVUgXGtD+TYjLrrdTiwaM8w2PUEOX38DlXPGMmo77JmnhDFGs8imueuSkec+lRf8Cp3eAM1X+e0\/tH4gSSNYsBcewBo+0C3fTw3B2uQ+MK4BgOUNwe6cY3Px3tq\/\/24nw\/v36cfQL8AvZTnKclAQAA","skull-owner":"dropheads:ENDERMAN"}},"19":{"==":"org.bukkit.inventory.ItemStack","v":2730,"type":"PLAYER_HEAD","amount":6,"meta":{"==":"ItemMeta","meta-type":"SKULL","display-name":"{\"translate\":\"%s %s\",\"with\":[{\"translate\":\"entity.minecraft.enderman\"},{\"translate\":\"Head\"}],\"italic\":false}","lore":["{\"text\":\"mob:enderman\",\"color\":\"dark_gray\",\"italic\":false}"],"internal":"H4sIAAAAAAAA\/03PTU6DQBwF8H9NTRBdeQ8TagumJi6I1HZIZ5B2iszsaJkKdKZt+FDhLu51rfcwnsA7uHAt7ly+vF9e8nQAHU7mm0rK23y3TqXQoEsiJeA0znf7RERxcTkizmiGbaKD3qK9yMtUFEegleKprHJR6ADQ0eAwiGQl4F3UrsHDxIhDV65qZLWZzg3poWx\/gbZBvbxGFlJtP7GtaT38Z80yujMl67sJ3\/rVUgXGtD+TYjLrrdTiwaM8w2PUEOX38DlXPGMmo77JmnhDFGs8imueuSkec+lRf8Cp3eAM1X+e0\/tH4gSSNYsBcewBo+0C3fTw3B2uQ+MK4BgOUNwe6cY3Px3tq\/\/24nw\/v36cfQL8AvZTnKclAQAA","skull-owner":"dropheads:ENDERMAN"}},"0":{"==":"org.bukkit.inventory.ItemStack","v":2730,"type":"DIAMOND","amount":36},"3":{"==":"org.bukkit.inventory.ItemStack","v":2730,"type":"EMERALD","amount":2},"4":{"==":"org.bukkit.inventory.ItemStack","v":2730,"type":"GOLD_INGOT","amount":11},"5":{"==":"org.bukkit.inventory.ItemStack","v":2730,"type":"IRON_NUGGET"},"6":{"==":"org.bukkit.inventory.ItemStack","v":2730,"type":"IRON_BLOCK","amount":64},"7":{"==":"org.bukkit.inventory.ItemStack","v":2730,"type":"IRON_BLOCK","amount":64},"8":{"==":"org.bukkit.inventory.ItemStack","v":2730,"type":"IRON_BLOCK","amount":64},"9":{"==":"org.bukkit.inventory.ItemStack","v":2730,"type":"IRON_BLOCK","amount":64}},"bedSpawnLocation":{"==":"org.bukkit.Location","world":"Killer_Island","x":9836.5,"y":63.0,"z":7665.5,"pitch":0.0,"yaw":-137.11954},"offHandItem":{"==":"org.bukkit.inventory.ItemStack","v":2730,"type":"AIR","amount":0},"potions":[],"inventoryContents":{"27":{"==":"org.bukkit.inventory.ItemStack","v":2730,"type":"DIAMOND_SHOVEL"},"28":{"==":"org.bukkit.inventory.ItemStack","v":2730,"type":"DIAMOND_PICKAXE","meta":{"==":"ItemMeta","meta-type":"UNSPECIFIC","display-name":"{\"text\":\"Drip\"}","enchants":{"DIG_SPEED":4,"LOOT_BONUS_BLOCKS":3,"MENDING":1,"DURABILITY":3},"repair-cost":1,"Damage":88}},"29":{"==":"org.bukkit.inventory.ItemStack","v":2730,"type":"CHAIN","amount":15},"10":{"==":"org.bukkit.inventory.ItemStack","v":2730,"type":"WHEAT"},"11":{"==":"org.bukkit.inventory.ItemStack","v":2730,"type":"NETHERRACK","amount":2},"33":{"==":"org.bukkit.inventory.ItemStack","v":2730,"type":"MOSS_BLOCK","amount":64},"12":{"==":"org.bukkit.inventory.ItemStack","v":2730,"type":"ENDER_PEARL","amount":16},"36":{"==":"org.bukkit.inventory.ItemStack","v":2730,"type":"DIAMOND_BOOTS","meta":{"==":"ItemMeta","meta-type":"UNSPECIFIC","enchants":{"PROTECTION_FALL":4,"MENDING":1,"DURABILITY":3},"repair-cost":3}},"37":{"==":"org.bukkit.inventory.ItemStack","v":2730,"type":"DIAMOND_LEGGINGS","meta":{"==":"ItemMeta","meta-type":"UNSPECIFIC","enchants":{"MENDING":1,"PROTECTION_ENVIRONMENTAL":3,"DURABILITY":3},"repair-cost":1}},"38":{"==":"org.bukkit.inventory.ItemStack","v":2730,"type":"DIAMOND_CHESTPLATE","meta":{"==":"ItemMeta","meta-type":"UNSPECIFIC","enchants":{"MENDING":1,"PROTECTION_ENVIRONMENTAL":4,"THORNS":2,"DURABILITY":3},"repair-cost":1}},"39":{"==":"org.bukkit.inventory.ItemStack","v":2730,"type":"DIAMOND_HELMET","meta":{"==":"ItemMeta","meta-type":"UNSPECIFIC","enchants":{"WATER_WORKER":1,"MENDING":1,"PROTECTION_ENVIRONMENTAL":4,"DURABILITY":3},"repair-cost":1}},"0":{"==":"org.bukkit.inventory.ItemStack","v":2730,"type":"DIAMOND_SWORD","meta":{"==":"ItemMeta","meta-type":"UNSPECIFIC","enchants":{"MENDING":1,"DAMAGE_ALL":3,"DURABILITY":3},"repair-cost":1}},"1":{"==":"org.bukkit.inventory.ItemStack","v":2730,"type":"DIAMOND_PICKAXE","meta":{"==":"ItemMeta","meta-type":"UNSPECIFIC","enchants":{"DIG_SPEED":2,"MENDING":1,"SILK_TOUCH":1},"repair-cost":1,"Damage":360}},"2":{"==":"org.bukkit.inventory.ItemStack","v":2730,"type":"DIAMOND_AXE","meta":{"==":"ItemMeta","meta-type":"UNSPECIFIC","enchants":{"DIG_SPEED":4,"LOOT_BONUS_BLOCKS":3,"MENDING":1},"repair-cost":1,"Damage":472}},"3":{"==":"org.bukkit.inventory.ItemStack","v":2730,"type":"DIAMOND_HOE","meta":{"==":"ItemMeta","meta-type":"UNSPECIFIC","enchants":{"DIG_SPEED":4,"LOOT_BONUS_BLOCKS":3,"DURABILITY":3},"Damage":128}},"4":{"==":"org.bukkit.inventory.ItemStack","v":2730,"type":"DIAMOND_SHOVEL","meta":{"==":"ItemMeta","meta-type":"UNSPECIFIC","enchants":{"DIG_SPEED":4,"MENDING":1,"DURABILITY":3},"repair-cost":1,"Damage":502}},"5":{"==":"org.bukkit.inventory.ItemStack","v":2730,"type":"WHEAT_SEEDS","amount":63},"6":{"==":"org.bukkit.inventory.ItemStack","v":2730,"type":"NETHER_QUARTZ_ORE","amount":13},"7":{"==":"org.bukkit.inventory.ItemStack","v":2730,"type":"BUCKET"},"8":{"==":"org.bukkit.inventory.ItemStack","v":2730,"type":"COOKED_BEEF","amount":39},"9":{"==":"org.bukkit.inventory.ItemStack","v":2730,"type":"DIAMOND_BLOCK"}},"armorContents":{"0":{"==":"org.bukkit.inventory.ItemStack","v":2730,"type":"DIAMOND_BOOTS","meta":{"==":"ItemMeta","meta-type":"UNSPECIFIC","enchants":{"PROTECTION_FALL":4,"MENDING":1,"DURABILITY":3},"repair-cost":3}},"1":{"==":"org.bukkit.inventory.ItemStack","v":2730,"type":"DIAMOND_LEGGINGS","meta":{"==":"ItemMeta","meta-type":"UNSPECIFIC","enchants":{"MENDING":1,"PROTECTION_ENVIRONMENTAL":3,"DURABILITY":3},"repair-cost":1}},"2":{"==":"org.bukkit.inventory.ItemStack","v":2730,"type":"DIAMOND_CHESTPLATE","meta":{"==":"ItemMeta","meta-type":"UNSPECIFIC","enchants":{"MENDING":1,"PROTECTION_ENVIRONMENTAL":4,"THORNS":2,"DURABILITY":3},"repair-cost":1}},"3":{"==":"org.bukkit.inventory.ItemStack","v":2730,"type":"DIAMOND_HELMET","meta":{"==":"ItemMeta","meta-type":"UNSPECIFIC","enchants":{"WATER_WORKER":1,"MENDING":1,"PROTECTION_ENVIRONMENTAL":4,"DURABILITY":3},"repair-cost":1}}},"stats":{"ex":"3.1238534","ma":"300","fl":"20","el":"55","hp":"20.0","xp":"0.92148113","txp":"32852","sa":"2.0","fd":"0.46416","ft":"-20","ra":"300"}}}